siki/__init__.py
siki/basics/AttributeDict.py
siki/basics/Convert.py
siki/basics/Exceptions.py
siki/basics/FileUtils.py
siki/basics/Hashcode.py
siki/basics/JsonUtils.py
siki/basics/Logger.py
siki/basics/TimeTicker.py
siki/basics/Untangle.py
siki/basics/Validators.py
siki/basics/__init__.py
siki/dstruct/BinaryTreeNode.py
siki/dstruct/CommonTreeNode.py
siki/dstruct/DictExtern.py
siki/dstruct/KeyValue.py
siki/dstruct/ListExtern.py
siki/dstruct/Queue.py
siki/dstruct/__init__.py
siki/interfaces/Switch.py
siki/interfaces/__init__.py
siki/numeric/Basics.py
siki/numeric/__init__.py
siki-0.1.6.dist-info/LICENSE
siki-0.1.6.dist-info/METADATA
siki-0.1.6.dist-info/WHEEL
siki-0.1.6.dist-info/top_level.txt
siki-0.1.6.dist-info/RECORD
