Metadata-Version: 2.1
Name: siki
Version: 0.1.6
Summary: A collection of tools that may be used to help users coding with Python in an easy way
Home-page: https://github.com/seagochen/Siki
Author: Orlando Chen
Author-email: seagochen@hotmail.com
License: UNKNOWN
Platform: UNKNOWN
Classifier: Programming Language :: Python :: 3
Classifier: License :: OSI Approved :: GNU General Public License v3 (GPLv3)
Classifier: Operating System :: OS Independent
Requires-Dist: pptree
